hmmer_tables/__init__.py
hmmer_tables/cleanup.py
hmmer_tables/cli.py
hmmer_tables/csv_iter.py
hmmer_tables/domtbl.py
hmmer_tables/output.py
hmmer_tables/path_like.py
hmmer_tables/query.py
hmmer_tables/tbl.py
hmmer_tables-1.0.2.dist-info/METADATA
hmmer_tables-1.0.2.dist-info/WHEEL
hmmer_tables-1.0.2.dist-info/entry_points.txt
hmmer_tables-1.0.2.dist-info/licenses/LICENSE
hmmer_tables-1.0.2.dist-info/RECORD
